dbflux/__init__.py
dbflux/base.py
dbflux/databases.py
dbflux/model.py
dbflux/utils.py
dbflux-1.0.2.dist-info/licenses/LICENSE
dbflux-1.0.2.dist-info/METADATA
dbflux-1.0.2.dist-info/WHEEL
dbflux-1.0.2.dist-info/top_level.txt
dbflux-1.0.2.dist-info/RECORD
