Metadata-Version: 2.4
Name: dbflux
Version: 1.0.2
Summary: A simple database management abstraction layer built on SQLAlchemy
Author-email: Abbas Bachari <abbas-bachari@hotmail.com>
License: MIT
Project-URL: homepage, https://github.com/abbas-bachari/dbflux
Project-URL: documentation, https://github.com/abbas-bachari/dbflux#readme
Project-URL: bug-tracker, https://github.com/abbas-bachari/dbflux/issues
Keywords: database,SQLAlchemy,ORM,Python
Classifier: Programming Language :: Python :: 3
Classifier: License :: OSI Approved :: MIT License
Classifier: Operating System :: OS Independent
Requires-Python: >=3.8
License-File: LICENSE
Requires-Dist: SQLAlchemy>=2.0.0
Dynamic: license-file
